{
	"serial" : 1,
	"revision" : 1,
	"mapPath": "DLC/Data/Serial/Res/Map", 
	"areaNum" : 35,
	"mapNum" : 121,
	"systemCallNames" : [
		"",
		"",
		"",
		"",
		""
	],
	"areaNames" : [
		"なし",
		"ワールドマップ",
		"なし",
		"なし",
		"なし",
		"オンラクの町",
		"海底神殿",
		"アースの洞窟",
		"エルフの城",
		"エルフの町",
		"海底神殿",
		"カオス神殿",
		"巨人の洞窟",
		"グルグ火山",
		"クレセントレイクの町",
		"賢者の洞窟",
		"コーネリアの城",
		"コーネリアの町",
		"氷の洞窟",
		"ガイアの町",
		"試練の城",
		"ミラージュの塔",
		"滝の裏の洞窟",
		"ドラゴンの洞窟",
		"ドワーフの洞窟",
		"西の城",
		"沼の洞窟",
		"浮遊城",
		"マトーヤの洞窟",
		"港町プラボカ",
		"メルモンドの町",
		"ルフェイン人の町",
		"キャラバン",
		"跳ね橋",
		"リュカーン砂漠"
	],
	"mapNames" : [
		"なし",
		"FF1ワールドマップ",
		"コーネリアの城１F",
		"コーネリアの城２F",
		"コーネリアの町",
		"コーネリアの町-宿屋",
		"コーネリアの町-道具屋",
		"コーネリアの町-武器屋",
		"コーネリアの町-防具屋",
		"コーネリアの町-教会",
		"コーネリアの町-LV1白魔法屋",
		"コーネリアの町-LV1黒魔法屋",
		"マトーヤの洞窟",
		"港町プラボカ",
		"港町プラボカ-宿屋",
		"港町プラボカ-道具屋",
		"港町プラボカ-武器屋",
		"港町プラボカ-防具屋",
		"港町プラボカ-教会",
		"港町プラボカ-LV2白魔法屋",
		"港町プラボカ-LV2黒魔法屋",
		"ドワーフの洞窟",
		"エルフの町",
		"エルフの町-宿屋",
		"エルフの町-道具屋",
		"エルフの町-武器屋",
		"エルフの町-防具屋",
		"エルフの町-教会",
		"エルフの町-LV3白魔法屋",
		"エルフの町-LV3黒魔法屋",
		"エルフの町-LV4白魔法屋",
		"エルフの町-LV4黒魔法屋",
		"エルフの城",
		"西の城",
		"メルモンドの町",
		"メルモンドの町-宿屋",
		"メルモンドの町-武器屋",
		"メルモンドの町-防具屋",
		"メルモンドの町-LV5白魔法屋",
		"メルモンドの町-LV5黒魔法屋",
		"賢者の洞窟",
		"クレセントレイクの町",
		"クレセントレイクの町-宿屋",
		"クレセントレイクの町-道具屋",
		"クレセントレイクの町-武器屋",
		"クレセントレイクの町-防具屋",
		"クレセントレイクの町-教会",
		"クレセントレイクの町-LV6白魔法屋",
		"クレセントレイクの町-LV6黒魔法屋",
		"ドラゴンの洞窟(A)",
		"ドラゴンの洞窟(B)",
		"ドラゴンの洞窟(C)",
		"オンラクの町",
		"オンラクの町-宿屋",
		"オンラクの町-道具屋",
		"オンラクの町-教会",
		"オンラクの町-LV7白魔法屋",
		"オンラクの町-LV7黒魔法屋",
		"キャラバン",
		"キャラバン-道具屋",
		"ガイアの町",
		"ガイアの町-宿屋",
		"ガイアの町-道具屋",
		"ガイアの町-武器屋・防具屋",
		"ガイアの町-武器屋・防具屋",
		"ガイアの町-教会",
		"ガイアの町-LV7白魔法屋",
		"ガイアの町-LV7黒魔法屋",
		"ガイアの町-LV8白魔法屋・黒魔法屋",
		"ガイアの町-LV8白魔法屋・黒魔法屋",
		"ルフェイン人の町",
		"ルフェイン人の町-LV8白魔法屋・黒魔法屋",
		"カオス神殿",
		"沼の洞窟B1F",
		"沼の洞窟B2F",
		"沼の洞窟B3F",
		"アースの洞窟B１F",
		"アースの洞窟B２F",
		"アースの洞窟B３F",
		"アースの洞窟B４F",
		"アースの洞窟B５F",
		"巨人の洞窟",
		"グルグ火山B１F",
		"グルグ火山B２F",
		"グルグ火山B３F・Ａ",
		"グルグ火山B３F・Ｂ",
		"グルグ火山B4F",
		"グルグ火山B５F",
		"氷の洞窟B１F",
		"氷の洞窟B２F・A",
		"氷の洞窟B３F・A",
		"氷の洞窟B２F・B",
		"氷の洞窟B３F・B",
		"試練の城１F",
		"試練の城２F",
		"試練の城３F",
		"海底神殿１F",
		"海底神殿２F",
		"海底神殿３F・A",
		"海底神殿３F・B",
		"海底神殿３F・C",
		"海底神殿４F・A",
		"海底神殿４F・B",
		"海底神殿５F",
		"滝の裏の洞窟",
		"ミラージュの塔１F",
		"ミラージュの塔２F",
		"ミラージュの塔３F",
		"浮遊城１F",
		"浮遊城２F",
		"浮遊城３F",
		"浮遊城４F",
		"浮遊城５F",
		"過去のカオス神殿１F",
		"過去のカオス神殿２F",
		"過去のカオス神殿３F",
		"過去のカオス神殿B１F",
		"過去のカオス神殿B２F",
		"過去のカオス神殿B３F",
		"過去のカオス神殿B４F",
		"過去のカオス神殿B５F"
	],
	"storageNames" : {
		"scenarioFlag1" : [
			"オープニング閲覧",
			"王との謁見",
			"セーラ救出",
			"コーネリア王の援助",
			"大陸に架かる橋",
			"リュートをもらう",
			"橋が架かる",
			"プロローグ閲覧",
			"マトーヤの目が見えない",
			"船入手",
			"クラウン入手",
			"水晶の目入手",
			"目覚めの薬入手",
			"王子の目覚め",
			"ニトロの火薬入手",
			"運河開通",
			"バンパイア撃破",
			"スタールビー入手",
			"巨人がスタールビーを食べる",
			"土の杖入手",
			"石板消去",
			"リッチ撃破",
			"カヌー入手",
			"マリリス撃破",
			"浮遊石入手",
			"飛行船入手",
			"ワープキューブ入手",
			"妖精のビン購入",
			"妖精の解放",
			"空気の水入手",
			"タル潜水艦使用可能",
			"ロゼッタ石入手",
			"ルフェイン語習得",
			"チャイム入手",
			"クラーケン撃破",
			"ティアマット撃破",
			"光と闇の融合",
			"石板消去2",
			"リッチ撃破2",
			"マリリス撃破2",
			"クラーケン撃破2",
			"ティアマット撃破2",
			"カオス撃破",
			"エンディング閲覧",
			"老人と話す",
			"ねずみのしっぽ入手",
			"クラスチェンジ",
			"アダマンタイト入手",
			"エクスカリバー入手"
		],
		"scenarioFlag2" : [],
		"scenarioFlag3" : [],
		"scenarioFlag4" : [],
		"treasureFlag1" : [
			"コーネリアの城-１F|てつのよろい|宝箱がある部屋に入るために、神秘の鍵が必要",
			"コーネリアの城-１F|テント|宝箱がある部屋に入るために、神秘の鍵が必要",
			"コーネリアの城-１F|コテージ|宝箱がある部屋に入るために、神秘の鍵が必要",
			"コーネリアの城-１F|サーベル|宝箱がある部屋に入るために、神秘の鍵が必要",
			"コーネリアの城-１F|ミスリルナイフ|宝箱がある部屋に入るために、神秘の鍵が必要",
			"カオス神殿（現在）|かわのぼうし|",
			"カオス神殿（現在）|ポーション|",
			"カオス神殿（現在）|テント|",
			"カオス神殿（現在）|ウェアバスター|宝箱がある部屋に入るために、神秘の鍵が必要",
			"カオス神殿（現在）|きんのはり|宝箱がある部屋に入るために、神秘の鍵が必要",
			"カオス神殿（現在）|ルーンブレード|宝箱がある部屋に入るために、神秘の鍵が必要",
			"マトーヤの洞窟|ポーション|",
			"マトーヤの洞窟|ポーション|",
			"マトーヤの洞窟|どくけし|",
			"エルフの城|ミスリルハンマー|宝箱がある部屋に入るために、神秘の鍵が必要",
			"エルフの城|800ギル|宝箱がある部屋に入るために、神秘の鍵が必要",
			"エルフの城|700ギル|宝箱がある部屋に入るために、神秘の鍵が必要",
			"エルフの城|せいどうのこて|宝箱がある部屋に入るために、神秘の鍵が必要",
			"西の城|ちからのつえ|宝箱がある部屋に入るために、神秘の鍵が必要",
			"西の城|フォールチョン|宝箱がある部屋に入るために、神秘の鍵が必要",
			"西の城|はがねのこて|宝箱がある部屋に入るために、神秘の鍵が必要",
			"沼の洞窟-Ｂ２Ｆ|680ギル-|別の宝箱と連動",
			"沼の洞窟-Ｂ２Ｆ|ダガー|",
			"沼の洞窟-Ｂ２Ｆ|ブロードソード-|別の宝箱と連動",
			"沼の洞窟-Ｂ２Ｆ|620ギル|",
			"沼の洞窟-Ｂ3Ｆ|フェニックスのお-|別の宝箱と連動",
			"沼の洞窟-Ｂ3Ｆ|295ギル|",
			"沼の洞窟-Ｂ3Ｆ|コテージ|",
			"沼の洞窟-Ｂ3Ｆ|どうのうでわ|",
			"沼の洞窟-Ｂ3Ｆ|385ギル|",
			"沼の洞窟-Ｂ3Ｆ|ぎんのうでわ|宝箱がある部屋に入るために、神秘の鍵が必要",
			"沼の洞窟-Ｂ3Ｆ|どくけし|宝箱がある部屋に入るために、神秘の鍵が必要",
			"沼の洞窟-Ｂ3Ｆ|1020ギル|宝箱がある部屋に入るために、神秘の鍵が必要",
			"ドワーフの洞窟|450ギル|",
			"ドワーフの洞窟|575ギル|",
			"ドワーフの洞窟|テント|宝箱がある部屋に入るために、神秘の鍵が必要",
			"ドワーフの洞窟|おおかぶと|宝箱がある部屋に入るために、神秘の鍵が必要",
			"ドワーフの洞窟|ウィルムキラー|宝箱がある部屋に入るために、神秘の鍵が必要",
			"ドワーフの洞窟|エーテル|宝箱がある部屋に入るために、神秘の鍵が必要",
			"ドワーフの洞窟|ポーション|宝箱がある部屋に入るために、神秘の鍵が必要",
			"ドワーフの洞窟|ミスリルメイル|宝箱がある部屋に入るために、神秘の鍵が必要",
			"ドワーフの洞窟|575ギル|宝箱がある部屋に入るために、神秘の鍵が必要",
			"ドワーフの洞窟|コテージ|宝箱がある部屋に入るために、神秘の鍵が必要",
			"アースの洞窟-Ｂ１Ｆ|1975ギル|",
			"アースの洞窟-Ｂ１Ｆ|880ギル|",
			"アースの洞窟-Ｂ１Ｆ|ポーション|",
			"アースの洞窟-Ｂ１Ｆ|どくけし|",
			"アースの洞窟-Ｂ１Ｆ|795ギル|",
			"アースの洞窟-Ｂ２Ｆ|さんごのつるぎ|",
			"アースの洞窟-Ｂ２Ｆ|テント|",
			"アースの洞窟-Ｂ２Ｆ|330ギル|",
			"アースの洞窟-Ｂ２Ｆ|5000ギル|",
			"アースの洞窟-Ｂ２Ｆ|かわのたて|",
			"アースの洞窟-Ｂ２Ｆ|575ギル|",
			"アースの洞窟-Ｂ３Ｆ|ねぶくろ|",
			"アースの洞窟-Ｂ３Ｆ|きんのはり|",
			"アースの洞窟-Ｂ３Ｆ|3400ギル|",
			"アースの洞窟-Ｂ３Ｆ|1020ギル|",
			"アースの洞窟-Ｂ４Ｆ|5450ギル|",
			"アースの洞窟-Ｂ４Ｆ|1250ギル|",
			"アースの洞窟-Ｂ４Ｆ|つえ|",
			"アースの洞窟-Ｂ４Ｆ|3400ギル|",
			"アースの洞窟-Ｂ４Ｆ|1455ギル|",
			"アースの洞窟-Ｂ４Ｆ|1250ギル|",
			"アースの洞窟-Ｂ４Ｆ|ミスリルのたて|",
			"アースの洞窟-Ｂ４Ｆ|テント|",
			"グルグ火山-Ｂ２Ｆ|ミスリルのかぶと|",
			"グルグ火山-Ｂ２Ｆ|1520ギル|",
			"グルグ火山-Ｂ２Ｆ|4150ギル|",
			"グルグ火山-Ｂ２Ｆ|グレートソード|",
			"グルグ火山-Ｂ２Ｆ|795ギル|",
			"グルグ火山-Ｂ２Ｆ|750ギル|",
			"グルグ火山-Ｂ２Ｆ|ミスリルのこて|",
			"グルグ火山-Ｂ２Ｆ|ミスリルのかぶと|",
			"グルグ火山-Ｂ２Ｆ|ハイポーション|",
			"グルグ火山-Ｂ２Ｆ|テント|",
			"グルグ火山-Ｂ２Ｆ|1760ギル|",
			"グルグ火山-Ｂ２Ｆ|1520ギル|",
			"グルグ火山-Ｂ２Ｆ|ミスリルのたて|",
			"グルグ火山-Ｂ２Ｆ|1455ギル|",
			"グルグ火山-Ｂ２Ｆ|ミスリルアクス|",
			"グルグ火山-Ｂ２Ｆ|1975ギル|",
			"グルグ火山-Ｂ２Ｆ|どくけし|",
			"グルグ火山-Ｂ２Ｆ|フェニックスのお|",
			"グルグ火山-Ｂ４Ｆ|2750ギル|",
			"グルグ火山-Ｂ４Ｆ|きんのはり-|別の宝箱と連動",
			"グルグ火山-Ｂ４Ｆ|1760ギル|",
			"グルグ火山-Ｂ４Ｆ|どくけし|",
			"グルグ火山-Ｂ４Ｆ|7340ギル|",
			"グルグ火山-Ｂ４Ｆ|ほのおのたて|",
			"グルグ火山-Ｂ４Ｆ|アイスブランド-|別の宝箱と連動",
			"グルグ火山-Ｂ４Ｆ|880ギル|",
			"グルグ火山-Ｂ４Ｆ|10ギル|",
			"グルグ火山-Ｂ４Ｆ|155ギル|",
			"グルグ火山-Ｂ４Ｆ|つえ|",
			"グルグ火山-Ｂ４Ｆ|1250ギル|",
			"グルグ火山-Ｂ４Ｆ|コテージ|",
			"グルグ火山-Ｂ４Ｆ|2000ギル|",
			"グルグ火山-Ｂ５Ｆ|フレイムメイル|",
			"氷の洞窟-Ｂ１Ｆ|エーテル|",
			"氷の洞窟-Ｂ１Ｆ|10000ギル|",
			"氷の洞窟-Ｂ１Ｆ|9500ギル|",
			"氷の洞窟-Ｂ１Ｆ|ねぶくろ|",
			"氷の洞窟-Ｂ１Ｆ|アイスシールド|",
			"氷の洞窟-Ｂ２Ｆ|フレームソード|",
			"氷の洞窟-Ｂ２Ｆ|ふく|",
			"氷の洞窟-Ｂ３Ｆ|ミスリルのこて|",
			"氷の洞窟-Ｂ３Ｆ|アイスアーマー|",
			"氷の洞窟-Ｂ３Ｆ|7900ギル|",
			"氷の洞窟-Ｂ３Ｆ|5454ギル|",
			"氷の洞窟-Ｂ３Ｆ|180ギル|",
			"氷の洞窟-Ｂ３Ｆ|9900ギル|",
			"氷の洞窟-Ｂ３Ｆ|5000ギル|",
			"氷の洞窟-Ｂ３Ｆ|12350ギル|",
			"滝の裏の洞窟|まどうしのつえ|",
			"滝の裏の洞窟|6400ギル|",
			"滝の裏の洞窟|リボン|",
			"滝の裏の洞窟|5000ギル|",
			"滝の裏の洞窟|13450ギル|",
			"滝の裏の洞窟|ディフェンダー|",
			"海底神殿-２Ｆ|7690ギル|",
			"海底神殿-２Ｆ|8135ギル|",
			"海底神殿-２Ｆ|5450ギル|",
			"海底神殿-２Ｆ|385ギル|",
			"海底神殿-２Ｆ|きょじんのこて|",
			"海底神殿-２Ｆ|9900ギル|",
			"海底神殿-２Ｆ|ライトアクス|",
			"海底神殿-２Ｆ|2750ギル|",
			"海底神殿-２Ｆ|リボン|",
			"海底神殿-２Ｆ|7340ギル|",
			"海底神殿-３Ｆ|2000ギル|",
			"海底神殿-３Ｆ|9900ギル|",
			"海底神殿-３Ｆ|450ギル|",
			"海底神殿-３Ｆ|110ギル|",
			"海底神殿-４Ｆ|ダイヤアーマー|",
			"海底神殿-４Ｆ|20ギル|",
			"海底神殿-４Ｆ|ライトアクス|",
			"海底神殿-４Ｆ|まじゅつのつえ|",
			"海底神殿-４Ｆ|12350ギル|",
			"海底神殿-５F|どくけし|",
			"海底神殿-５F|ダイヤシールド|",
			"海底神殿-５F|9000ギル|",
			"海底神殿-５F|1760ギル|",
			"海底神殿-５F|ダイヤのうでわ|",
			"海底神殿-５F|4150ギル|",
			"海底神殿-５F|5000ギル|",
			"海底神殿-５F|2750ギル|",
			"海底神殿-５F|10000ギル|",
			"海底神殿-５F|10ギル|",
			"海底神殿-５F|ダイヤのかぶと|",
			"海底神殿-５F|ダイヤのこて|",
			"ミラージュの塔-１Ｆ|テント|",
			"ミラージュの塔-１Ｆ|シャープソード|",
			"ミラージュの塔-１Ｆ|イージスのたて|",
			"ミラージュの塔-１Ｆ|3400ギル|",
			"ミラージュの塔-１Ｆ|2750ギル|",
			"ミラージュの塔-１Ｆ|いやしのかぶと|",
			"ミラージュの塔-１Ｆ|18010ギル|",
			"ミラージュの塔-１Ｆ|800ギル|",
			"ミラージュの塔-２Ｆ|8135ギル|",
			"ミラージュの塔-２Ｆ|サンブレード|",
			"ミラージュの塔-２Ｆ|ドラゴンメイル|",
			"ミラージュの塔-２Ｆ|12350ギル|",
			"ミラージュの塔-２Ｆ|7900ギル|",
			"ミラージュの塔-２Ｆ|7600ギル|",
			"ミラージュの塔-２Ｆ|10000ギル|",
			"ミラージュの塔-２Ｆ|13000ギル|",
			"ミラージュの塔-２Ｆ|トールハンマー|",
			"ミラージュの塔-２Ｆ|コテージ|",
			"浮遊城-１Ｆ|9900ギル|",
			"浮遊城-１Ｆ|まもりのゆびわ|",
			"浮遊城-１Ｆ|ポーション|",
			"浮遊城-１Ｆ|6720ギル|",
			"浮遊城-１Ｆ|4150ギル|",
			"浮遊城-１Ｆ|いやしのかぶと|",
			"浮遊城-１Ｆ|7900ギル|",
			"浮遊城-１Ｆ|180ギル|",
			"浮遊城-１Ｆ|5000ギル|",
			"浮遊城-１Ｆ|レイズサーベル|",
			"浮遊城-２Ｆ|880ギル|",
			"浮遊城-２Ｆ|ダイヤの小手|",
			"浮遊城-２Ｆ|13000ギル|",
			"浮遊城-２Ｆ|リボン|",
			"浮遊城-２Ｆ|ミスリルのかぶと|",
			"浮遊城-２Ｆ|ダイヤシールド|",
			"浮遊城-２Ｆ|コテージ|",
			"浮遊城-２Ｆ|しろのローブ|",
			"浮遊城-２Ｆ|くろのローブ|",
			"浮遊城-３Ｆ|きんのはり|",
			"浮遊城-３Ｆ|まもりのゆびわ|",
			"浮遊城-３Ｆ|4150ギル|",
			"浮遊城-３Ｆ|まもりのマント|",
			"浮遊城-３Ｆ|3400ギル|",
			"浮遊城-３Ｆ|ふく×2|",
			"浮遊城-３Ｆ|サスケのかたな|",
			"浮遊城-３Ｆ|6400ギル|",
			"浮遊城-３Ｆ|ポーション|",
			"浮遊城-３Ｆ|8135ギル|",
			"浮遊城-３Ｆ|9000ギル|",
			"浮遊城-３Ｆ|9500ギル|",
			"浮遊城-３Ｆ|5450ギル|",
			"浮遊城-３Ｆ|きんのはり|",
			"カオス神殿（過去）-３F|エーテルドライ|",
			"カオス神殿（過去）-３F|エリクサー|",
			"カオス神殿（過去）-Ｂ２Ｆ|まもりのゆびわ|",
			"カオス神殿（過去）-Ｂ２Ｆ|まもりのマント|",
			"カオス神殿（過去）-Ｂ２Ｆ|サスケのかたな|",
			"カオス神殿（過去）-Ｂ２Ｆ|ラストエリクサー|",
			"カオス神殿（過去）-Ｂ４Ｆ|マサムネ|",
			"試練の城-２Ｆ|ガントレット|",
			"試練の城-３Ｆ|いやしのつえ|",
			"試練の城-３Ｆ|コテージ|",
			"試練の城-３Ｆ|ルビーのうでわ|",
			"試練の城-３Ｆ|1455ギル|",
			"試練の城-３Ｆ|アイスブランド|",
			"試練の城-３Ｆ|7340ギル|",
			"試練の城-３Ｆ|はがねのこて|",
			"試練の城-３Ｆ|ガントレット|"
		],
		"treasureFlag2" : [],
		"treasureFlag3" : [],
		"treasureFlag4" : [],
		"scenarioVariables" : [
			"",
			"",
			"",
			"",
			"",
			"",
			"",
			"",
			"",
			"",
			"",
			"",
			"",
			"",
			"",
			""
		],
		"areaLocalVariables" : [
			["","","","","","","",""],
			["","","","","","","",""],
			["","","","","","","",""],
			["","","","","","","",""],
			["","","","","","","",""],
			["","","","","","","",""],
			["","","","","","","",""],
			["","","","","","","",""],
			["","","","","","","",""],
			["","","","","","","",""],
			["","","","","","","",""],
			["","","","","","","",""],
			["","","","","","","",""],
			["","","","","","","",""],
			["","","","","","","",""]
		],
		"mapLocalVariables" : [
			["","","","","","","",""],
			["","","","","","","",""],
			["","","","","","","",""],
			["","","","","","","",""],
			["","","","","","","",""],
			["","","","","","","",""],
			["","","","","","","",""],
			["","","","","","","",""],
			["","","","","","","",""],
			["","","","","","","",""],
			["","","","","","","",""],
			["","","","","","","",""],
			["","","","","","","",""],
			["","","","","","","",""],
			["","","","","","","",""]
		]
	},
	"messages" : [
		{"id":"MSG_OP", "text":"この世は暗黒に包まれている。風はやみ、海は荒れ…大地は腐ってゆく..."},
		{"id":"MSG_KON_CTY_01", "text":"ここは夢の都コーネリアよ。"},
		{"id":"MSG_KON_CTY_02", "text":"私は踊り子！え？私と一緒に踊りたいって？ウフフッ…。"},
		{"id":"MSG_KON_CTY_03", "text":"あれ、まだいたの？橋を渡って大陸に行くんでしょう？そんなに私と踊..."},
		{"id":"MSG_KON_CTY_04", "text":"プラボカは港町よ。海賊なら『船』を持ってるかもね。"},
		{"id":"MSG_KON_CTY_05", "text":"もうマトーヤには会った？目が見えなくなって困っているらしいの…。..."},
		{"id":"MSG_KON_CTY_06", "text":"もう西の城へは行った？<PAGE>なんでも沼の洞窟にある『クラウン』が..."},
		{"id":"MSG_KON_CTY_07", "text":"ほら、西の城の王様に『クラウン』を届けてあげなくちゃ。でも…何か..."},
		{"id":"MSG_KON_CTY_08", "text":"マトーヤの『水晶の目』は盗まれたままで、まだ見つかっていないらし..."},
		{"id":"MSG_KON_CTY_09", "text":"『目覚めの薬』を使えば、エルフの王子も目を覚ますんじゃないかしら..."},
		{"id":"MSG_KON_CTY_10", "text":"コーネリア城のとざされた部屋は、『神秘の鍵』があれば入れるらしい..."},
		{"id":"MSG_KON_CTY_11", "text":"ドワーフ族のネリクって人が強力な火薬を探してるらしいの。何に使う..."},
		{"id":"MSG_KON_CTY_12", "text":"私、もう何も知らないわ。いいから踊りましょ！"},
		{"id":"MSG_KON_CTY_13", "text":"戦士たちよ、クリスタルに祝福を…。"},
		{"id":"MSG_KON_CTY_14", "text":"お願いです。王女様を助け出してください。"},
		{"id":"MSG_KON_CTY_15", "text":"コーネリアを出て北に行ったところに、マトーヤという魔女が住んでい..."},
		{"id":"MSG_KON_CTY_16", "text":"予言者のルカーン様は三日月を目指すと言って、この町を出ていってし..."},
		{"id":"MSG_KON_CTY_17", "text":"行動範囲を広げるためには『船』が必要不可欠じゃな。<PAGE>『船』が..."},
		{"id":"MSG_KON_CTY_18", "text":"『カヌー』とかいうものがあれば、川を渡ることができるらしいな。<P..."},
		{"id":"MSG_KON_CTY_19", "text":"ところで、『空を飛ぶ船』というのを知っとるか？<PAGE>エルフの予言..."},
		{"id":"MSG_KON_CTY_20", "text":"おぬしたち、光の戦士にしてはいまひとつ貫禄がないのう…。称号とや..."},
		{"id":"MSG_KON_CTY_21", "text":"試練の城へは行ったようじゃな。でも、勇者の証とやらはまだ持ってい..."},
		{"id":"MSG_KON_CTY_22", "text":"なんじゃ？『ネズミのしっぽ』なんぞ持って…。<PAGE>まあ、何もない..."},
		{"id":"MSG_KON_CTY_23", "text":"ところで、三日月とは本当の月ではないと思うんじゃが…。<PAGE>わし..."},
		{"id":"MSG_KON_CTY_24", "text":"教えてやれることは何もないわ。<PAGE>クリスタルの輝きが戻ったら、..."},
		{"id":"MSG_KON_CTY_25", "text":"王は、光の戦士が現れ、さらわれた王女を救ってくれるとかたく信じて..."},
		{"id":"MSG_KON_CTY_27", "text":"お願いです。セーラ様を助け出してください！"},
		{"id":"MSG_KON_CTY_28", "text":"マトーヤは、目が悪いんだって。『水晶の目』がないと何も見えないら..."},
		{"id":"MSG_KON_CTY_29", "text":"私は昔、はるか東にある港町プラボカに住んでいました。今では、海賊..."},
		{"id":"MSG_KON_CTY_30", "text":"井戸です。入れそうで入れない井戸です。"},
		{"id":"MSG_KON_CTY_31", "text":"すんだ水に顔を映してみましょう…。<PAGE>まあ汚い！さあ、この水で..."},
		{"id":"MSG_MAP0A01_10", "text":"王は、伝説の光の戦士を探しておいでだ。<PAGE>ムッ、そのクリスタル..."},
		{"id":"MSG_KON_INN_01", "text":"「装備」についてワシが教えてしんぜよう。聞きたいか？"},
		{"id":"MSG_KON_INN_02", "text":"装備は「武器」と「防具」に分かれているのじゃ。<PAGE>「武器」を装..."},
		{"id":"MSG_KON_INN_03", "text":"「魔法」については私が説明してやろう。聞いてゆくか？"},
		{"id":"MSG_KON_INN_04", "text":"魔法は「白魔法」と「黒魔法」に分けられておる。<PAGE>「白魔法」は..."},
		{"id":"MSG_KON_INN_05", "text":"「アイテム」のことなら私におまかせじゃ！せっかくだから、聞いてい..."},
		{"id":"MSG_KON_INN_06", "text":"「ポーション」や「毒消し」は、たくさん持っていてそんはないぞ。<P..."},
		{"id":"MSG_KON_INN_07", "text":"行く手をはばむ魔物について聞きたいのか…？"},
		{"id":"MSG_KON_INN_08", "text":"魔物にはいろいろな種類がいて、それぞれに弱点がある…。<PAGE>弱点..."},
		{"id":"MSG_KON_CAS_01", "text":"私が王妃のジェーンです。どうか娘を…セーラを無事助け出してくださ..."},
		{"id":"MSG_KON_CAS_02", "text":"セーラを助けていただいて…なんとお礼を言ってよいか…！"},
		{"id":"MSG_KON_CAS_03", "text":"エーン、エーン…！姉…様が…。"},
		{"id":"MSG_KON_CAS_04", "text":"姉様が帰ってきたの！お兄ちゃんたちのおかげね！ありがとう！<PAGE>..."},
		{"id":"MSG_KON_CAS_05", "text":"王は、伝説の光の戦士を探しておいでだ。<PAGE>ムッ、そのクリスタル..."},
		{"id":"MSG_KON_CAS_06", "text":"私は、コーネリア城の警備という大役をおおせつかっています！<PAGE>..."},
		{"id":"MSG_KON_CAS_07", "text":"お妃様は、悲しみのあまり部屋に閉じこもったままです…。おいたわし..."},
		{"id":"MSG_KON_CAS_08", "text":"おお、光の戦士…！セーラ様を助け出してくださり、ありがとうござい..."},
		{"id":"MSG_KON_CAS_09", "text":"お願い！セーラ様を助けてあげて！"},
		{"id":"MSG_KON_CAS_10", "text":"光の戦士…なの？あのルカーンの予言の？"},
		{"id":"MSG_KON_CAS_11", "text":"かつてガーランドは国いちばんのナイトだったんだ。<PAGE>だが、力に..."},
		{"id":"MSG_KON_CAS_12", "text":"代々コーネリアの王女に伝わる美しき『リュート』には、悪の扉を打ち..."},
		{"id":"MSG_KON_CAS_13", "text":"私たちの祖先は４００年前、この宝物庫に武器を封印し、その鍵をエル..."},
		{"id":"MSG_KON_CAS_14", "text":"この宝物庫は『神秘の鍵』で封印されています。"},
		{"id":"MSG_KON_CAS_15", "text":"お願いです。王女様を助け出してください。"},
		{"id":"MSG_KON_CAS_16", "text":"さあ！今こそ、その鍵で扉を開ける時です！<PAGE>中にある道具の数々..."},
		{"id":"MSG_KON_CAS_17", "text":"光の戦士たちがようやく現れてくれた…！この時をどんなに待ちわびた..."},
		{"id":"MSG_KON_CAS_18", "text":"セーラは、そなたらのことをいつも気にかけているようだ。"},
		{"id":"MSG_KON_CAS_20", "text":"よければ…ずっとコーネリアで…<PAGE>いえ…なんでもありません。さ..."},
		{"id":"MSG_KON_CAS_23", "text":"セーラ様をさらったガーランドは、城の北にあるカオスの神殿に逃げ込..."},
		{"id":"MSG_KON_CAS_25", "text":"町にいる踊り子は、いろいろな情報を持っているのじゃ。<PAGE>道に迷..."},
		{"id":"MSG_KON_CAS_26", "text":"『ニトロの火薬』を手に入れた。"},
		{"id":"MSG_EKKEN_01", "text":"王は、伝説の光の戦士を探しておいでだ。<PAGE>ムッ、そのクリスタル..."},
		{"id":"MSG_EKKEN_02", "text":"旅の者よ、そなたらがクリスタルをたずさえているというのはまことか..."},
		{"id":"MSG_EKKEN_03", "text":"ルカーンの予言…。『この世、暗黒に染まりし時、４人の光の戦士現れ..."},
		{"id":"MSG_EKKEN_04", "text":"しかし、この者たちが、予言にある光の戦士だとはかぎりませぬ。"},
		{"id":"MSG_EKKEN_05", "text":"だが、クリスタルを持つ戦士が、いま目の前におる…。偶然とは思えぬ..."},
		{"id":"MSG_EKKEN_06", "text":"この国のナイトであったガーランドがセーラ姫をさらい、このコーネリ..."},
		{"id":"MSG_EKKEN_07", "text":"そなたらが目指すのは北の大陸と聞いた。大陸への橋は失われて久しく..."},
		{"id":"MSG_HELPSERA_04", "text":"よくぞ王女を助け出してくれた…。そなたらこそ、ルカーンの予言にあ..."},
		{"id":"MSG_HELPSERA_05", "text":"約束通り、北の大陸への橋をかけよう。<PAGE>そなたらが、４つのクリ..."},
		{"id":"MSG_LUTE_01", "text":"お待ちください…！"},
		{"id":"MSG_LUTE_02", "text":"これは、コーネリア国の王女に代々伝わる『リュート』です。<PAGE>ガ..."},
		{"id":"MSG_LUTE_03", "text":"『リュート』を手に入れた。"},
		{"id":"MSG_CHS_01", "text":"キィ…キィ…。"},
		{"id":"MSG_CHS_02", "text":"４匹のカオスにより、さえぎられていたクリスタルの輝き…。<PAGE>そ..."},
		{"id":"MSG_CHS_03", "text":"闇のクリスタルは、不気味に輝いている。わずかな空気のゆがみを感じ..."},
		{"id":"MSG_CHS_04", "text":"鍵がかかっている。"},
		{"id":"MSG_CHS_06", "text":"それは…我々が追い求めつづけてきた４つの輝きではないか！その輝き..."},
		{"id":"MSG_CHS_08", "text":"中心にある闇のクリスタルを４つの輝きで照らすのです！<PAGE>２００..."},
		{"id":"MSG_CHS_10", "text":"私たちは、天空人です…。<PAGE>世界滅亡の原因を突き止め、この神殿..."},
		{"id":"MSG_CHS_12", "text":"カオスの呪いによって、このような姿に変えられてから、私たちは言葉..."},
		{"id":"MSG_CHS_13", "text":"石板が床に置かれている…。そこはかとなく邪悪な空気を感じる…！"},
		{"id":"MSG_CHS_14", "text":"この扉は『神秘の鍵』によって封印されている…。"},
		{"id":"MSG_FUSION_01", "text":"火、土、水、風…４つの輝くクリスタルを闇のクリスタルに重ね合わせ..."},
		{"id":"MSG_HELPSERA_01", "text":"王女の命とひきかえに、コーネリアはついに私のものとなる…。"},
		{"id":"MSG_HELPSERA_02", "text":"何者だ、きさまたち…！？<PAGE>そうか…国王の手先か…。だが、私が..."},
		{"id":"MSG_HELPSERA_03", "text":"あなたがたが…助けてくれたのですね…？<PAGE>私は、コーネリア国の..."},
		{"id":"MSG_LAST_01", "text":"覚えているか…？コーネリア国一のナイトと呼ばれたこの私を…。"},
		{"id":"MSG_LAST_02", "text":"今から２０００年後の未来…おまえたちに倒されたガーランドだ…！"},
		{"id":"MSG_LAST_03", "text":"確かにあの時、私は倒された…。<PAGE>だが、あの時、４つの力が私を..."},
		{"id":"MSG_LAST_04", "text":"ここに来た私は４匹のカオスを未来へと送り込んだ…。"},
		{"id":"MSG_LAST_05", "text":"そしてまた、４つの力を使い、おまえたちに殺される未来の私をここへ..."},
		{"id":"MSG_LAST_06", "text":"２０００年のち…私の記憶は失われている。"},
		{"id":"MSG_LAST_07", "text":"だが、また私は、ここに戻るのだ！おまえたちは、ここで永久に死に…..."},
		{"id":"MSG_BRIDGE_01", "text":"国王のご命令だ。ルカーンの予言のため、力になれと…！"},
		{"id":"MSG_BRIDGE_02", "text":"この橋が、予言と関係あるのか？"},
		{"id":"MSG_BRIDGE_03", "text":"ここコーネリアに彼らが現れたそうだ…。４人の光の戦士たちが…！"},
		{"id":"MSG_PRL_01", "text":"かくして…探求の旅は始まった。４人の若者は光の戦士として、自らに..."},
		{"id":"MSG_SHIP_01", "text":"この海賊ビッケ様に逆らうとは、いい度胸してるじゃねぇか。やろうど..."},
		{"id":"MSG_SHIP_02", "text":"へい！こてんぱんでさ！"},
		{"id":"MSG_SHIP_03", "text":"すまねえ…オレがバカだった。もう悪さはしねえ…！<PAGE>おわびにオ..."},
		{"id":"MSG_SHIP_04", "text":"『船』を手に入れた。"},
		{"id":"MSG_PBK_01", "text":"頼む！助けてくれ！"},
		{"id":"MSG_PBK_02", "text":"アルディの海には魔物がたくさんいるようです。どうかお気をつけて！..."},
		{"id":"MSG_PBK_03", "text":"くそっ…！海賊の奴らめ！我が物顔で町を荒らしやがって！"},
		{"id":"MSG_PBK_04", "text":"北の方には、港はないらしいな。『船』は港にしか上陸できないぞ。"},
		{"id":"MSG_PBK_05", "text":"オレは、心を入れかえたんだ。マジメに仕事して、町いちばんの働き者..."},
		{"id":"MSG_PBK_06", "text":"あなたがたのおかげで、もう海賊におびえることもありません。ありが..."},
		{"id":"MSG_PBK_07", "text":"海の向こうにはエルフたちが住んでるんだって！<PAGE>でもね…王子様..."},
		{"id":"MSG_PBK_08", "text":"わしは西の彼方にあるメルモンドの町から、やっとのことで逃げてきた..."},
		{"id":"MSG_PBK_09", "text":"なんだ、おまえら？海賊ビッケ一味に逆らおうってのか！？"},
		{"id":"MSG_PBK_10", "text":"ま…まいりました…。"},
		{"id":"MSG_ELF_CAS_01", "text":"私たちの王子が、アストスの呪いで眠ったまま、目を覚まさないのです..."},
		{"id":"MSG_ELF_CAS_02", "text":"西の洞窟には悪魔が住んでいるらしい…。大地が腐り始めているのはど..."},
		{"id":"MSG_ELF_CAS_04", "text":"エルフは鍵を預かっているのです。いつか現れる光の戦士…。彼らにそ..."},
		{"id":"MSG_ELF_CAS_05", "text":"どんな薬でもせんじることのできる魔女のウワサを耳にしたよ。たしか..."},
		{"id":"MSG_ELF_CAS_06", "text":"それは『目覚めの薬』だね！その薬ならば、王子の眠りを覚ますことが..."},
		{"id":"MSG_ELF_CAS_07", "text":"ダークエルフの王、アストスは突然この城にやってきて…<PAGE>王子に..."},
		{"id":"MSG_ELF_CAS_08", "text":"王子がお目覚めになりました！ありがとうございます！"},
		{"id":"MSG_ELF_CAS_09", "text":"アルディの海、その西のはじにある洞窟には、ドワーフたちが住んでる..."},
		{"id":"MSG_ELF_CAS_10", "text":"この宝物庫は『神秘の鍵』で封印されています。"},
		{"id":"MSG_ELF_CAS_11", "text":"王子はアストスの呪いで、もう５年も眠りつづけているのだ…。<PAGE>..."},
		{"id":"MSG_ELF_CAS_12", "text":"おかげで王子も目覚めました。あなたがたには感謝しております。<PAG..."},
		{"id":"MSG_ELF_CAS_13", "text":"スヤ…スヤ…。"},
		{"id":"MSG_ELF_CAS_14", "text":"おかげでこの通り元気になった。ありがとう…光の戦士たちよ…！"},
		{"id":"MSG_AWAKEELF_01", "text":"これは…！<PAGE>この『目覚めの薬』ならば王子も呪いから解き放たれ..."},
		{"id":"MSG_AWAKEELF_02", "text":"王子！王子…！？"},
		{"id":"MSG_AWAKEELF_03", "text":"ずっと…悪い夢を見ていた…。これは、まだ…夢の続きなのか…？"},
		{"id":"MSG_AWAKEELF_04", "text":"君たちは…伝説の戦士…！？どうやら夢ではないようだな…。<PAGE>古..."},
		{"id":"MSG_AWAKEELF_05", "text":"『神秘の鍵』を手に入れた。"},
		{"id":"MSG_ELF_CTY_01", "text":"王子を助けてください！ああ…どうすればいいの？"},
		{"id":"MSG_ELF_CTY_02", "text":"王子がお目覚めになりました！ありがとうございます！"},
		{"id":"MSG_ELF_CTY_03", "text":"王子が目覚めなければ、妖精王は誕生せず…ダークエルフの闇の力がエ..."},
		{"id":"MSG_ELF_CTY_04", "text":"『飛空艇』という天かける船が、どこかに埋まっているという言い伝え..."},
		{"id":"MSG_ELF_CTY_05", "text":"ダークエルフの王、アストス…奴の行方は誰も知らないのです。"},
		{"id":"MSG_ELF_CTY_07", "text":"昔、西に向かって旅をしたことがあるんだ。古びた城に迷い込んじゃっ..."},
		{"id":"MSG_ELF_CTY_08", "text":"アストスを倒してくれたのですね！ああ、これでエルフにも平和が！"},
		{"id":"MSG_ELF_CTY_09", "text":"ああ…王子！妖精王になられるはずだったのに…。"},
		{"id":"MSG_ELF_CTY_11", "text":"ミスリル銀で作った剣や鎧は頑丈で、すごい威力なんだ。使ってみなよ..."},
		{"id":"MSG_ELF_CTY_12", "text":"私は予言者です。しかるべき時がくれば予言が降りてくるでしょう…。..."},
		{"id":"MSG_ELF_CTY_13", "text":"三日月の下の砂の海…。『浮遊石』の力によって大空に巨大な帆が浮か..."},
		{"id":"MSG_ELF_CTY_15", "text":"三日月の上の暗き穴…燃える山のさらに北…。『浮遊石』は、そこに眠..."},
		{"id":"MSG_ELF_CTY_16", "text":"リンク、ここに眠る…。"},
		{"id":"MSG_ELF_CTY_17", "text":"墓標だ…。"},
		{"id":"MSG_WST_CAS_01", "text":"ダークエルフの王、アストスにだまされ、この城も荒れ果ててしまった..."},
		{"id":"MSG_WST_CAS_02", "text":"キィ…キィ…。"},
		{"id":"MSG_WST_CAS_03", "text":"この扉は『神秘の鍵』によって封印されている…。"},
		{"id":"MSG_WST_CAS_04", "text":"スヤ…スヤ…。"},
		{"id":"MSG_ASTOS_01", "text":"ファファファ…！まんまとだまされおって…。バカな奴らよ。<PAGE>わ..."},
		{"id":"MSG_ASTOS_02", "text":"きさまらの持つ『クラウン』と、わしの持つ『水晶の目』…<PAGE>この..."},
		{"id":"MSG_ASTOS_03", "text":"逆らってもむだなこと…力ずくで奪ってくれるわ！"},
		{"id":"MSG_ASTOS_04", "text":"『水晶の目』を手に入れた。"},
		{"id":"MSG_PND_01", "text":"キィ…キィ…。"},
		{"id":"MSG_PND_02", "text":"この扉は『神秘の鍵』によって封印されている…。"},
		{"id":"MSG_GET_CROWN_01", "text":"『クラウン』を手に入れた。"},
		{"id":"MSG_AWAKEPOT_01", "text":"おお、『水晶の目』か？ほれ！さっさと返さぬか！<PAGE>ただとは言わ..."},
		{"id":"MSG_AWAKEPOT_02", "text":"おおっ！見える！目が見えるぞよっ！"},
		{"id":"MSG_AWAKEPOT_03", "text":"『目覚めの薬』を手に入れた。"},
		{"id":"MSG_MATOYA_01", "text":"イタタ…ッ！"},
		{"id":"MSG_MATOYA_02", "text":"目が…目が…！"},
		{"id":"MSG_MATOYA_03", "text":"『水晶の目』がないと何も見えんわい…。"},
		{"id":"MSG_MATOYA_04", "text":"誰だ？私の『水晶の目』を盗みおったのは…！"},
		{"id":"MSG_MAT_02", "text":"なんだい？もう、あんたらに用はないよ！思ったより、いい男でもなか..."},
		{"id":"MSG_MAT_03", "text":"フシギナ　ジュモンサ　サッサカサ！トクレセン　タボュシッダ　サッ..."},
		{"id":"MSG_DWF_CAV_01", "text":"伝説の金属である『アダマンタイト』さえあれば、幻の剣が作れるかも..."},
		{"id":"MSG_DWF_CAV_02", "text":"戦士たちよ、おぬしらならエクスカリバーを正しく使ってくれるじゃろ..."},
		{"id":"MSG_DWF_CAV_03", "text":"『水晶の目』があれば、目が見えない人でも物を見ることができるんだ..."},
		{"id":"MSG_DWF_CAV_04", "text":"大地が腐ってきている。西の方から、だんだんと…。"},
		{"id":"MSG_DWF_CAV_05", "text":"大地が元に戻ってきました！光の戦士、あなたたちのおかげです！"},
		{"id":"MSG_DWF_CAV_06", "text":"鍛冶屋のスミスには会ったかい？"},
		{"id":"MSG_DWF_CAV_07", "text":"この音かい？村の裏でネリクじいさんが岩を砕いてる音さね。"},
		{"id":"MSG_DWF_CAV_08", "text":"ネリクじいさんは偉大な人だ。尊敬できるドワーフだよ。"},
		{"id":"MSG_DWF_CAV_09", "text":"ラリホーっと！"},
		{"id":"MSG_DWF_CAV_10", "text":"「腕輪」は「鎧」にも負けない強い守備力を持っているんだ。代わりに..."},
		{"id":"MSG_DWF_CAV_12", "text":"あんたたち、運河は見たかい？やっぱりネリクじいさんはすげえドワー..."},
		{"id":"MSG_DWF_CAV_13", "text":"おれは『浮遊石』ってのを探してるんだ。なんだって空に浮かべること..."},
		{"id":"MSG_DWF_CAV_14", "text":"『ニトロの火薬』は、その昔、城の宝物庫にしまわれちまったらしい…..."},
		{"id":"MSG_DWF_CAV_16", "text":"ええい！巨大な岩が邪魔をしとる！運河の開通まで、あと一歩だという..."},
		{"id":"MSG_DWF_CAV_17", "text":"ダメダメ、それはサンプルじゃよ！使い物にはならんのじゃ。"},
		{"id":"MSG_DWF_CAV_18", "text":"この扉は『神秘の鍵』によって封印されている…。"},
		{"id":"MSG_CANAL_01", "text":"これは…『ニトロの火薬』！<PAGE>この爆破力をもってすれば、すぐに..."},
		{"id":"MSG_CANAL_02", "text":"これでよし…と！"},
		{"id":"MSG_CANAL_03", "text":"これで、いまいましい岩ともおさらばじゃ。"},
		{"id":"MSG_CANAL_04", "text":"何しとるんじゃ！今から爆破するんじゃぞ！命が惜しければ、避難せん..."},
		{"id":"MSG_CANAL_05", "text":"運河の向こうには、どんな世界があるのか楽しみじゃ！"},
		{"id":"MSG_GET_EXCALIBER_01", "text":"これは…『アダマンタイト』！？"},
		{"id":"MSG_GET_EXCALIBAR_02", "text":"よし！これを使って、わしが最高の剣を作ってやろう。"},
		{"id":"MSG_GET_EXCALIBAR_03", "text":"完成したぞ！こいつは、今まで手がけた中でも最高のできじゃぞ！"},
		{"id":"MSG_GET_EXCALIBAR_04", "text":"さ、持ってゆくがよい！"},
		{"id":"MSG_GET_EXCALIBAR_05", "text":"『エクスカリバー』を手に入れた。"},
		{"id":"MSG_LEARN_01", "text":"ちょっと、その石を見せてみたまえ。"},
		{"id":"MSG_LEARN_02", "text":"おお…ッ！こ、これこそ『ロゼッタ石』ではないか！"},
		{"id":"MSG_LEARN_03", "text":"これさえあれば、ルフェイン語の解読が可能になる…！"},
		{"id":"MSG_LEARN_04", "text":"なるほど…！わかったぞ…！そうか…！そういうことだったのか…！！..."},
		{"id":"MSG_LEARN_05", "text":"いいだろう。お礼に、君たちにも教えてやろう。"},
		{"id":"MSG_LEARN_06", "text":"よし！これで君たちもルフェイン語がわかるようになったはずだ。"},
		{"id":"MSG_MMD_CTY_01", "text":"大地が腐ってきているんだよ。アースの洞窟に住むバンパイアの仕業な..."},
		{"id":"MSG_MMD_CTY_02", "text":"この町メルモンドも、昔は豊かな土に恵まれ、とても美しいところだっ..."},
		{"id":"MSG_MMD_CTY_03", "text":"バンパイアに襲われて教会も壊れ、町はひどい状態だ…。大地の荒廃は..."},
		{"id":"MSG_MMD_CTY_04", "text":"あんたら、もしかして…光の戦士かい？"},
		{"id":"MSG_MMD_CTY_05", "text":"戦士たちよ、クリスタルに祝福を…。"},
		{"id":"MSG_MMD_CTY_06", "text":"バンパイアが倒れても大地はどんどん腐っていくようだ。なぜなんだ…..."},
		{"id":"MSG_MMD_CTY_07", "text":"この町の南、悪魔のしっぽと呼ばれる半島にはアースの洞窟がある。<P..."},
		{"id":"MSG_MMD_CTY_08", "text":"おおっ…！土のクリスタルに輝きが戻ったのか？"},
		{"id":"MSG_MMD_CTY_09", "text":"洞窟に住んでる巨人は石を食べるらしいぜ。<PAGE>石だったらなんでも..."},
		{"id":"MSG_MMD_CTY_10", "text":"学者のウネといえば知らぬものなどいない大天才だ。<PAGE>なにっ！？..."},
		{"id":"MSG_MMD_CTY_12", "text":"北には昔、非常に栄えた文明があったらしい。今では荒れ果ててしまっ..."},
		{"id":"MSG_MMD_CTY_14", "text":"あら！あなたたち、ずいぶん立派になったわね！"},
		{"id":"MSG_MMD_CTY_15", "text":"古代の人々は、何かの力で船を空に浮かべていたという話だ…。"},
		{"id":"MSG_MMD_CTY_16", "text":"あれ、飛空艇だろ！本当にあったんだ…！"},
		{"id":"MSG_MMD_CTY_17", "text":"ワシは、ドワーフの村からやってきたワッツというものだ。<PAGE>大地..."},
		{"id":"MSG_MMD_CTY_18", "text":"光の戦士たち…あなたがたのおかげです。大地に緑が戻ってきています..."},
		{"id":"MSG_MMD_CTY_19", "text":"南のはしの洞窟にサーダというものが住んでおる。あやつは、とても物..."},
		{"id":"MSG_MMD_CTY_20", "text":"農家をやっとります。"},
		{"id":"MSG_MMD_CTY_21", "text":"バンパイアが倒れても大地はますます腐っていく…。<PAGE>なぜなんだ..."},
		{"id":"MSG_MMD_CTY_22", "text":"お父さんがやってる店に寄っていってね！"},
		{"id":"MSG_MMD_CTY_23", "text":"土のクリスタルに輝きが戻れば、大地に再び命が宿るでしょう。緑が再..."},
		{"id":"MSG_MMD_CTY_24", "text":"光の戦士たち…あなたがたのおかげです。大地が元に戻っていきます！..."},
		{"id":"MSG_MMD_CTY_25", "text":"墓標だ…。"},
		{"id":"MSG_MAP01_01", "text":"『スタールビー』を手に入れた。"},
		{"id":"MSG_LICH_01", "text":"誰だ…我に話しかけるのは…。"},
		{"id":"MSG_LICH_02", "text":"我は…大地の力を喰らう者なり…。"},
		{"id":"MSG_LICH_03", "text":"人間ふぜいに…邪魔立てはさせぬぞ…土のカオス…リッチのな…！"},
		{"id":"MSG_VAMPIRE_01", "text":"この世界のすべてのものは、死に絶えてゆく運命なのだ…。<PAGE>封印..."},
		{"id":"MSG_VAMPIRE_02", "text":"運命を変えることはできぬ…。<PAGE>人間ごときが…この不老不死のバ..."},
		{"id":"MSG_ERH_CAV_01", "text":"キィ…キィ…。"},
		{"id":"MSG_ERH_CAV_02", "text":"石板が床に置かれている…。邪悪なオーラが立ちのぼっている…！"},
		{"id":"MSG_ERH_CAV_03", "text":"土の祭壇…。大地の力がわきでるところだ。"},
		{"id":"MSG_GIANT_RUBYEAT_01", "text":"そ、それは『スタールビー』…！？<PAGE>お、おまえら！それをくれた..."},
		{"id":"MSG_GIANT_RUBYEAT_02", "text":"モグモグ…。<PAGE>んー…うめえ…ッ！！やっぱりルビーが最高にうま..."},
		{"id":"MSG_GIA_CAV_01", "text":"この道は、誰も通すもんかっ！"},
		{"id":"MSG_SAG_CAV_01", "text":"戦士たちよ、クリスタルに祝福を…。"},
		{"id":"MSG_GET_STICK_01", "text":"バンパイアを倒したのはそなたたちか。<PAGE>しかし、奴とてしもべに..."},
		{"id":"MSG_GET_STICK_02", "text":"『土の杖』を手に入れた。"},
		{"id":"MSG_GET_CANOE_01", "text":"よくぞ土のカオスを倒し、クリスタルの輝きを取り戻してくれた。<PAG..."},
		{"id":"MSG_GET_CANOE_02", "text":"『カヌー』を手に入れた。"},
		{"id":"MSG_CLK_CTY_01", "text":"だんな様は、旅ばかりなされて帰ってきてもお昼寝ばかり。<PAGE>ちょ..."},
		{"id":"MSG_CLK_CTY_02", "text":"スヤ…スヤ…。"},
		{"id":"MSG_CLK_CTY_03", "text":"おれは『浮遊石』をもう１０年も追い求めているんだ。<PAGE>どうも、..."},
		{"id":"MSG_CLK_CTY_04", "text":"我々１２人の賢者は星と予言に導かれ、この地にやってきたのだ…。"},
		{"id":"MSG_CLK_CTY_05", "text":"この世界に存在する４つのクリスタル…。<PAGE>今はその輝きが失われ..."},
		{"id":"MSG_CLK_CTY_06", "text":"４つの力は、その中心にあるカオスの神殿に集まっている…。<PAGE>４..."},
		{"id":"MSG_CLK_CTY_07", "text":"火、土、水、風…この４つの力で、この世のすべては成り立っておる…..."},
		{"id":"MSG_CLK_CTY_08", "text":"４つの輝きが戻ったようだな…！<PAGE>その輝きを力に変えることが、..."},
		{"id":"MSG_CLK_CTY_09", "text":"４つの力の源は世界に散らばるそれぞれの祭壇だ。<PAGE>そこに根付い..."},
		{"id":"MSG_CLK_CTY_10", "text":"そなたたちの記憶は失われたようだが、そなたたちは、この地に迷い込..."},
		{"id":"MSG_CLK_CTY_11", "text":"４匹のカオスはすべての時代を支配しようとしている…。<PAGE>４００..."},
		{"id":"MSG_CLK_CTY_12", "text":"輪になった時の鎖…。憎しみの生み出したその輪を過去へ向かい、断ち..."},
		{"id":"MSG_CLK_CTY_13", "text":"土のカオスは大地を腐敗させてゆく…。"},
		{"id":"MSG_CLK_CTY_14", "text":"４００年前から始まった災いの数々…。<PAGE>しかし、それらが真に始..."},
		{"id":"MSG_CLK_CTY_15", "text":"火のカオスが現れた時、すべては焼きつくされるだろう…。"},
		{"id":"MSG_CLK_CTY_16", "text":"時がめぐっているのが見える…。２０００年前に飛んだ何かが世界崩壊..."},
		{"id":"MSG_CLK_CTY_17", "text":"４つのクリスタルの輝きを取り戻し、ここへ戻ってくるがよい。その時..."},
		{"id":"MSG_CLK_CTY_18", "text":"繰り返される２０００年の輪廻…憎しみの創りだす、ゆがんだ運命…。..."},
		{"id":"MSG_CLK_CTY_19", "text":"４つの輝きを我らの下へ…！それができるのは光の戦士、そなたたちだ..."},
		{"id":"MSG_CLK_CTY_20", "text":"力とは、正しき方向に使わねばならぬ…。"},
		{"id":"MSG_CLK_CTY_21", "text":"この町の西にあるグルグ火山、そこに眠っていた火のカオスが２００年..."},
		{"id":"MSG_CLK_CTY_22", "text":"４００年前に風が…２００年前に水が…そして土と火も…。<PAGE>この..."},
		{"id":"MSG_CLK_CTY_23", "text":"わが名は、ルカーン…。<PAGE>見える…憎しみの輪廻が…。伝説に導か..."},
		{"id":"MSG_CLK_CTY_24", "text":"墓標だ…。"},
		{"id":"MSG_GRG_MNT_01", "text":"火の祭壇…。火の力がわきでるところだ。"},
		{"id":"MSG_MARILITH_01", "text":"土のカオスを倒し、このマリリスの眠りをさまたげたのはおまえたちか..."},
		{"id":"MSG_MARILITH_02", "text":"土と水のカオスを倒し、このマリリスの眠りをさまたげたのはおまえた..."},
		{"id":"MSG_MARILITH_03", "text":"土と風のカオスを倒し、このマリリスの眠りをさまたげたのはおまえた..."},
		{"id":"MSG_MARILITH_04", "text":"土、水、風…３つのカオスを倒し、このマリリスの眠りをさまたげたの..."},
		{"id":"MSG_MARILITH_05", "text":"燃え盛る火の力は、この私の物じゃ…！邪魔をする者は地獄の業火で焼..."},
		{"id":"MSG_GET_FLOAT_01", "text":"『浮遊石』を手に入れた。"},
		{"id":"MSG_MAP1B_01", "text":"『飛空艇』を手に入れた。"},
		{"id":"MSG_GET_MOUSE_01", "text":"『ネズミのしっぽ』を手に入れた。"},
		{"id":"MSG_TRIAL_CAS_01", "text":"ほう、『クラウン』を持っておるのか。そなたたちの腕は確かなようだ..."},
		{"id":"MSG_TRIAL_CAS_02", "text":"許しなき者は、試練を受けられぬ！"},
		{"id":"MSG_CLASS_CHG_01", "text":"勇者と呼べる人間は久しくいなかったが…おまえたちならば、真の勇者..."},
		{"id":"MSG_CLASS_CHG_02", "text":"その『ネズミのしっぽ』こそ勇気と力の証…。"},
		{"id":"MSG_CLASS_CHG_03", "text":"さあ、望むがよい…。おまえたちに勇者の称号を与えよう…！"},
		{"id":"MSG_DRG_CAV_01", "text":"我は、竜王バハムート…。<PAGE>真の勇気と力を持つものに称号を与え..."},
		{"id":"MSG_DRG_CAV_02", "text":"戦士たちよ、クリスタルに祝福を…。"},
		{"id":"MSG_DRG_CAV_03", "text":"私を恐れぬとは…なかなか肝がすわっている…。"},
		{"id":"MSG_DRG_CAV_04", "text":"竜王バハムートには、お会いしたか？王は勇気あるものに称号を授けて..."},
		{"id":"MSG_DRG_CAV_05", "text":"我々ドラゴンは精神を試すため、北東にある試練の城へ行き勇気の証を..."},
		{"id":"MSG_DRG_CAV_06", "text":"勇気の証は、時としてその形を変える。見た目には惑わされないことだ..."},
		{"id":"MSG_DRG_CAV_07", "text":"はるか昔…北の地には美しい神殿や機械仕掛けの城が数多くそびえ立っ..."},
		{"id":"MSG_DRG_CAV_08", "text":"この地に人間がやってくるとは、めずらしいこともあるものだ。<PAGE>..."},
		{"id":"MSG_DRG_CAV_09", "text":"ガルディア諸島のドラゴンは無益な殺生を好まぬのだ。"},
		{"id":"MSG_DRG_CAV_10", "text":"はるか昔…ドラゴンと人間が、共に生きた時代もあったのだが…。"},
		{"id":"MSG_DRG_CAV_11", "text":"勇気の証は、真に勇気ある者のみが手にすることができるものだ。"},
		{"id":"MSG_DRG_CAV_12", "text":"ここは竜王バハムートの部屋…。失礼のないようにな。"},
		{"id":"MSG_DRG_CAV_13", "text":"竜王バハムートは、その心眼で真の勇気を見抜くのだ。"},
		{"id":"MSG_OXYALE_01", "text":"あなたたちは…！私をビンから助け出してくれた人ね。<PAGE>ごめんな..."},
		{"id":"MSG_OXYALE_02", "text":"その水からは、限りなく空気がわき出してくるのよ…！"},
		{"id":"MSG_OXYALE_03", "text":"『空気の水』を手に入れた。"},
		{"id":"MSG_GAI_CTY_01", "text":"別に悪いことしたとは思ってないね。捕まえた妖精は、おれのもんだ。..."},
		{"id":"MSG_GAI_CTY_02", "text":"ルフェイン語を研究している、なんとかって学者の話を聞いたんだが…..."},
		{"id":"MSG_GAI_CTY_03", "text":"この町の泉に住んでいる妖精を最近見かけないのよ…。いったいどうし..."},
		{"id":"MSG_GAI_CTY_04", "text":"親父がいつも言ってたんだ。西にある城は勇気と力を試す城だって。"},
		{"id":"MSG_GAI_CTY_05", "text":"この町の泉の底には、妖精にしかくむことのできない、『空気の水』が..."},
		{"id":"MSG_GAI_CTY_06", "text":"空をかけめぐり、天高く城を築いたという天空人の伝説が、今もこの地..."},
		{"id":"MSG_GAI_CTY_07", "text":"ヤーニクルム砂漠にある塔には誰も入ることができない…。<PAGE>まる..."},
		{"id":"MSG_GAI_CTY_08", "text":"あのほうきは仕事をさぼってばっかりで、ホントにしょうがないんだよ..."},
		{"id":"MSG_GAI_CTY_09", "text":"アー　イソガシ…　サッサカサ！"},
		{"id":"MSG_GAI_CTY_10", "text":"鷹の翼って知ってるかい？あそこの言葉は全然わからないんだ。"},
		{"id":"MSG_GAI_CTY_11", "text":"えっ！？鷹の翼の言葉がわかるってのかい！？"},
		{"id":"MSG_GAI_CTY_12", "text":"ここはガイアの町。外の人からは鷹の目と呼ばれています。<PAGE>南に..."},
		{"id":"MSG_GAI_CTY_13", "text":"助けてくれてありがとう！『空気の水』は役に立った？<PAGE>限りなく..."},
		{"id":"MSG_GAI_CTY_14", "text":"信じらんなーい。あなたたち外の人でしょ。どうやってこんな山頂まで..."},
		{"id":"MSG_GAI_CTY_15", "text":"私、見たんです…！夜空を光り輝くものが西の方へ飛んでいくのを！"},
		{"id":"MSG_SUBMARINE_01", "text":"それは『空気の水』…。"},
		{"id":"MSG_SUBMARINE_02", "text":"ずっと、あなたがたを待っていました。"},
		{"id":"MSG_SUBMARINE_03", "text":"お願いです！人魚たちを救ってください…！"},
		{"id":"MSG_ORK_CTY_01", "text":"『空気の水』って聞いたことあるかい？"},
		{"id":"MSG_ORK_CTY_02", "text":"２００年前の出来事じゃが、神殿が海に沈んだという話がある。<PAGE>..."},
		{"id":"MSG_ORK_CTY_03", "text":"ここも２００年前までは立派な町だったらしいよ。"},
		{"id":"MSG_ORK_CTY_04", "text":"私の足を見て！素敵でしょ！<PAGE>足があるって楽しいわ。ほら、見て..."},
		{"id":"MSG_ORK_CTY_05", "text":"キャラバンのアンダーヒルが何か変なもんを持ってたぜ。"},
		{"id":"MSG_ORK_CTY_06", "text":"ルフェイン語とは、昔、天空人と呼ばれていた人々が使っていた言葉の..."},
		{"id":"MSG_ORK_CTY_07", "text":"それが『ロゼッタ石』！？早く兄のウネのところに行って、その石を渡..."},
		{"id":"MSG_ORK_CTY_08", "text":"海の底に沈んだ神殿にはたくさんの財宝があるらしいわ。<PAGE>金、銀..."},
		{"id":"MSG_ORK_CTY_09", "text":"コペのやつ、光ってる何かが落ちるのを見たとか、寝ぼけたことばっか..."},
		{"id":"MSG_ORK_CTY_10", "text":"ウィー…ヒック…！くそっ！おれに構うなよ！ちくしょう！<PAGE>魚が..."},
		{"id":"MSG_ORK_CTY_11", "text":"あんたの足は、自分のものかい？"},
		{"id":"MSG_ORK_CTY_12", "text":"２００年も前の話だが…オンラクの神殿は水の力をたたえ、たいそう栄..."},
		{"id":"MSG_ORK_CTY_13", "text":"神秘なる水の力がよみがえった！これでまた昔のように、この国も栄え..."},
		{"id":"MSG_ORK_CTY_14", "text":"海の底の人魚たちを救いたくて、タルで潜水艦を作ったの。<PAGE>でも..."},
		{"id":"MSG_ORK_CTY_15", "text":"おまえたちも戦士のようだな。私は竜王に称号をもらうため、試練の城..."},
		{"id":"MSG_ORK_CTY_16", "text":"これは驚いた…！人間が、称号を得たというのか…！"},
		{"id":"MSG_ORK_CTY_17", "text":"あたしのお父さんはキャラバンなの。今は西の砂漠に行ってるわ。<PAG..."},
		{"id":"MSG_ORK_CTY_18", "text":"おれがコペだよ。光ってるもの…？<PAGE>ああ、見たよ。北の滝の方だ..."},
		{"id":"MSG_ORK_CTY_19", "text":"タルに乗りますか？"},
		{"id":"MSG_ORK_CTY_20", "text":"すんだ水に顔を映してみましょう…。<PAGE>まあ汚い！さあ、この水で..."},
		{"id":"MSG_ORK_CTY_21", "text":"墓標だ…。"},
		{"id":"MSG_ORK_CTY_22", "text":"井戸です。入れそうで入れない井戸です。"},
		{"id":"MSG_MAP04_01", "text":"『ロゼッタ石』を手に入れた。"},
		{"id":"MSG_KRAKEN_01", "text":"フォ…　フォ……　フォ………ニンゲンドモガ　ココマデタドリツクト..."},
		{"id":"MSG_KRAKEN_02", "text":"ダガ　ミズノ　カオス　クラーケンニスイチュウデ　カナウト　オモッ..."},
		{"id":"MSG_SEA_DAN_01", "text":"水の祭壇…。水の力がわきでるところだ。"},
		{"id":"MSG_SEA_DAN_02", "text":"ああ……！私の祈りに応えてくださったのですね！"},
		{"id":"MSG_SEA_DAN_03", "text":"私たち人魚は海の光を失うと水の泡になって消えてしまうの…。"},
		{"id":"MSG_SEA_DAN_04", "text":"私たちの仲間のひとりが、上の世界を見に行ったまま、帰ってこなくな..."},
		{"id":"MSG_SEA_DAN_05", "text":"あなたたち水の中で息ができるの？どうして？どうして！？"},
		{"id":"MSG_SEA_DAN_06", "text":"海を救ってください。水のクリスタルの輝きを取り戻して…。"},
		{"id":"MSG_SEA_DAN_07", "text":"ありがとうございました！この辺り一帯も昔のように美しい海に戻るで..."},
		{"id":"MSG_SEA_DAN_08", "text":"このまま海の輝きを取り戻せずに、水の泡になってしまうのかしら…。..."},
		{"id":"MSG_SEA_DAN_09", "text":"ねえ、そのクリスタルって伝説にあるものじゃない？あなたたちいった..."},
		{"id":"MSG_SEA_DAN_10", "text":"ここは神殿の最上階です。水のカオス、クラーケンは神殿のいちばん下..."},
		{"id":"MSG_SEA_DAN_11", "text":"東の大陸の砂漠に建っているミラージュの塔ってあるでしょう。<PAGE>..."},
		{"id":"MSG_SEA_DAN_12", "text":"水のカオスがいる限り、海の輝きはどんどん弱まっていくわ…。"},
		{"id":"MSG_SEA_DAN_13", "text":"タルに乗りますか？"},
		{"id":"MSG_GET_CHIME_01", "text":"伝説の戦士たちよ。この『チャイム』を持ってゆくがよい！<PAGE>これ..."},
		{"id":"MSG_GET_CHIME_02", "text":"『チャイム』を手に入れた。"},
		{"id":"MSG_RFE_CTY_01", "text":"ル…パ…ガミ…ド？"},
		{"id":"MSG_RFE_CTY_02", "text":"我々に、古くから語り継がれる伝説がある。<PAGE>天空の文明が滅び４..."},
		{"id":"MSG_RFE_CTY_03", "text":"光をたずさえた戦士…！おお！伝説は本当だった！"},
		{"id":"MSG_RFE_CTY_04", "text":"我々は、５人の戦士に最後の望みをたくした…。<PAGE>しかし、カオス..."},
		{"id":"MSG_RFE_CTY_05", "text":"天空高くにある浮遊城。あれは、我々の祖先がかつて住んでいたところ..."},
		{"id":"MSG_RFE_CTY_06", "text":"４匹のカオスを操る者がいる。我々は、そう推測した…。<PAGE>その居..."},
		{"id":"MSG_RFE_CTY_07", "text":"この世界を形作っている火、土、水、風、４つの力…。<PAGE>我々は、..."},
		{"id":"MSG_RFE_CTY_08", "text":"４００年前のことだ。我々は高度な文明を築いていた…。<PAGE>天空よ..."},
		{"id":"MSG_RFE_CTY_09", "text":"浮遊城は、天空よりはるか彼方…青き星の海に浮かんでいる。"},
		{"id":"MSG_RFE_CTY_10", "text":"天空人は、儀式によって祖先から代々と、記憶を受け継いできた種族…..."},
		{"id":"MSG_RFE_CTY_11", "text":"祖先が作った機械人形たちは今も動いているのだろうか…？"},
		{"id":"MSG_RFE_CTY_12", "text":"我々は、ルフェイン人。かつては天空人と呼ばれた空に住んでいた種族..."},
		{"id":"MSG_RFE_CTY_13", "text":"ミラージュの塔は我々ルフェイン人のシンボルだ。"},
		{"id":"MSG_RFE_CTY_14", "text":"我々は、風のカオスであるティアマットと死闘を繰り広げた…。<PAGE>..."},
		{"id":"MSG_RFE_CTY_15", "text":"天空人の力の源であった風の力…今は、あのティアマットにさえぎられ..."},
		{"id":"MSG_RFE_CTY_16", "text":"すんだ水に顔を映してみましょう…。<PAGE>まあ汚い！さあ、この水で..."},
		{"id":"MSG_GET_WARPCUBE_01", "text":"ズット…　マッテイタ……<PAGE>コノ　キューブ　モッテイッテ……フ..."},
		{"id":"MSG_GET_WARPCUBE_02", "text":"ギギ…ガガ……。"},
		{"id":"MSG_GET_WARPCUBE_03", "text":"『ワープキューブ』を手に入れた。"},
		{"id":"MSG_FAL_DAN_01", "text":"キィ…キィ…。"},
		{"id":"MSG_MRG_DAN_01", "text":"オ…　オオ…！ゴシュジンサマ…ズット…　マッテイマシタ…！"},
		{"id":"MSG_MRG_DAN_02", "text":"ワタシタチノ　ナカマ…ニシノ　カナタニ　タビニ　デタ…<PAGE>『ワ..."},
		{"id":"MSG_MRG_DAN_03", "text":"『ワープキューブ』ヲ　ツカエバテンクウノ　ハルカ　カナタ…フユウ..."},
		{"id":"MSG_WND_DAN_01", "text":"ティアマット…　カイセキチュウ…イゼン…　ジャクテン　ミアタラズ..."},
		{"id":"MSG_WND_DAN_02", "text":"コノ　テンボウマドカラセカイノ　ダイチガ　ミワタセマス。"},
		{"id":"MSG_WND_DAN_03", "text":"風の祭壇…。風の力がわきでるところだ。"},
		{"id":"MSG_WND_DAN_04", "text":"『アダマンタイト』を手に入れた。"},
		{"id":"MSG_LOOK_WINDOW_01", "text":"展望窓から世界が見渡せる。<PAGE>火、土、水、風…４つの力が霧のよ..."},
		{"id":"MSG_TIAMAT_01", "text":"土のカオス、リッチを倒し、この風のカオスのところまで、よくぞたど..."},
		{"id":"MSG_TIAMAT_02", "text":"リッチ、マリリス…<PAGE>２つのカオスを倒し、この風のカオスのとこ..."},
		{"id":"MSG_TIAMAT_03", "text":"リッチ、クラーケン…<PAGE>２つのカオスを倒し、この風のカオスのと..."},
		{"id":"MSG_TIAMAT_04", "text":"リッチ、マリリス、クラーケン…<PAGE>３つのカオスを倒し、この風の..."},
		{"id":"MSG_TIAMAT_05", "text":"その瞳に焼き付けて死ぬがよい…風のカオス、ティアマットの姿…！！..."},
		{"id":"MSG_EPL_01", "text":"時の鎖は、断ち切られた…。"},
		{"id":"MSG_EPL_02", "text":"２０００年の時を超えた無限の戦いは終わり、世界に平和が訪れた。"},
		{"id":"MSG_EPL_03", "text":"再び、この世を４つの光が照らしだし、その力は風を、水を、土を…そ..."},
		{"id":"MSG_EPL_04", "text":"２０００年の時を超えてめぐるガーランドの憎しみ。"},
		{"id":"MSG_EPL_05", "text":"それは、ささいな運命のすれ違いから始まったものだった。"},
		{"id":"MSG_EPL_06", "text":"だが、そのすれ違いは、この世界を導くはずの４つの力に増幅され、４..."},
		{"id":"MSG_EPL_07", "text":"世には魔物がはびこり、すべては暗黒に染められた…。"},
		{"id":"MSG_EPL_08", "text":"しかし、それも終わった。"},
		{"id":"MSG_EPL_09", "text":"戦士たちの活躍によって、すべての力は正しい方向へと向けられたのだ..."},
		{"id":"MSG_EPL_10", "text":"４人の戦士は、再び時を超え元の世界へと帰ってゆく。"},
		{"id":"MSG_EPL_11", "text":"世界は４人がよく知っている元の姿に戻っているはずだ。"},
		{"id":"MSG_EPL_12", "text":"そこにはセーラ姫やジェーン王妃たちが待っている。もちろん４人のよ..."},
		{"id":"MSG_EPL_13", "text":"あれは、いつのことだろう…。"},
		{"id":"MSG_EPL_14", "text":"ある日突然、すべてがくるいだしたのは…。その時の輪は無限につづく..."},
		{"id":"MSG_EPL_15", "text":"しかし、４人の勇気がそれを変えた。"},
		{"id":"MSG_EPL_16", "text":"この世を暗黒に染めた、４つの力をこの世を照らす力へと。"},
		{"id":"MSG_EPL_17", "text":"４人の戦士の戦いを覚えているものはいないはずだった。"},
		{"id":"MSG_EPL_18", "text":"そう…彼らの戦いによって、無限の時の輪は正しい流れを取り戻したか..."},
		{"id":"MSG_EPL_19", "text":"だが…人々は、心のどこかに記憶されているその戦いを、幻想の物語と..."},
		{"id":"MSG_EPL_20", "text":"ドワーフやエルフの村、ドラゴンたち…。宇宙にまで手を伸ばしながら..."},
		{"id":"MSG_EPL_21", "text":"さあ、戦士たちが帰ってくる。"},
		{"id":"MSG_EPL_22", "text":"２０００年の時を超えて…。"},
		{"id":"MSG_EPL_23", "text":"もう、たどり着くころだろう。"},
		{"id":"MSG_EPL_24", "text":"戦士たちは、戦いの記憶を心の底にしまいこみ、この世界をしずかに見..."},
		{"id":"MSG_EPL_25", "text":"忘れないでほしい。"},
		{"id":"MSG_EPL_26", "text":"この世界の力が、いつも正しい方向を向くべきだということを。"},
		{"id":"MSG_EPL_27", "text":"光の力を闇の力に変えてはならないということを。"},
		{"id":"MSG_EPL_28", "text":"そして、真のクリスタルは、その胸の中にあるということを…。"},
		{"id":"MSG_EPL_29", "text":"そう…２０００年の時を超え、戦っていたのは君なのだから。"},
		{"id":"MSG_EPL_30", "text":"すべてのものに輝きを…。"},
		{"id":"MSG_MAP0A01_01", "text":"いらっしゃい！ここに泊まると３００ギルだよ。いいかな？どうかな？..."},
		{"id":"MSG_MAP0A01_02", "text":"また来てくださいね！"},
		{"id":"MSG_MAP0A01_03", "text":"お休みなさい！"},
		{"id":"MSG_MAP0A01_04", "text":"お金が足りないようですね。"},
		{"id":"MSG_MAP0A01_05", "text":"魂よ、よみがえれーっ！"},
		{"id":"MSG_MAP0A01_06", "text":"<SITAI>を生き返らせるには<KINGAKU>ギルかかるが、いいかな？"},
		{"id":"MSG_MAP0A01_07", "text":"誰を生き返らせるのかね？"},
		{"id":"MSG_MAP0A01_08", "text":"誰も助けはいらないようです…。くじけずに頑張りなさい。"},
		{"id":"MSG_MAP0A01_09", "text":"<SITAI>を生き返らせるのかね？"},
		{"id":"MSG_OTHER_11", "text":"宝箱の中に「(ITEM_N)」を見つけた！"},
		{"id":"MSG_OTHER_12", "text":"もうこれ以上持つことはできないよ！"},
		{"id":"MSG_OTHER_13", "text":"宝箱の中は空っぽだっ！"},
		{"id":"MSG_OTHER_16", "text":"宝箱の中に(NUM)ギルを見つけた！"},
		{"id":"MSG_OTHER_14", "text":"ここから地上に戻ることができます。戻りますか？"},
		{"id":"MSG_OTHER_15", "text":"ギル"},
		{"id":"MSG_OTHER12_01", "text":"はい"},
		{"id":"MSG_OTHER12_02", "text":"いいえ"},
		{"id":"MSG_OTHER12_03", "text":"みぎ"},
		{"id":"MSG_OTHER12_04", "text":"ひだり"},
		{"id":"MSG_OTHER12_05", "text":"ギル"}
	]
}


