{
  "id":13,
  "layers":[
    {
      "draworder":"topdown",
      "id":14,
      "name":"GroundObject",
      "objects":[
        {
          "gid":2048,
          "height":16,
          "id":48,
          "name":"\u6d77\u8cca(\u4e0b\u3063\u7aef)",
          "properties":[
            {
              "name":"accept_action_direction",
              "type":"int",
              "value":15
            },
            {
              "name":"action_id",
              "type":"int",
              "value":4
            },
            {
              "name":"affected",
              "type":"bool",
              "value":false
            },
            {
              "name":"asset_id",
              "type":"int",
              "value":54
            },
            {
              "name":"birdview_puppet",
              "type":"bool",
              "value":false
            },
            {
              "name":"direction",
              "type":"int",
              "value":4
            },
            {
              "name":"entity_id",
              "type":"int",
              "value":46
            },
            {
              "name":"eye_contact",
              "type":"bool",
              "value":true
            },
            {
              "name":"flight_altitude_ratio",
              "type":"float",
              "value":1
            },
            {
              "name":"idling",
              "type":"bool",
              "value":false
            },
            {
              "name":"link_object_id",
              "type":"int",
              "value":0
            },
            {
              "name":"message_key",
              "type":"string",
              "value":"MSG_PBK_09"
            },
            {
              "name":"move_interval_id",
              "type":"int",
              "value":0
            },
            {
              "name":"move_speed_id",
              "type":"int",
              "value":0
            },
            {
              "name":"move_step",
              "type":"int",
              "value":0
            },
            {
              "name":"move_type",
              "type":"int",
              "value":1
            },
            {
              "name":"move_while_display_message",
              "type":"bool",
              "value":false
            },
            {
              "name":"object_id",
              "type":"int",
              "value":0
            },
            {
              "name":"object_type",
              "type":"int",
              "value":6
            },
            {
              "name":"pushed",
              "type":"bool",
              "value":true
            },
            {
              "name":"script_id",
              "type":"int",
              "value":0
            },
            {
              "name":"target_character_status_id",
              "type":"int",
              "value":0
            },
            {
              "name":"turn_around",
              "type":"bool",
              "value":true
            },
            {
              "name":"visible_minimap",
              "type":"bool",
              "value":false
            }
          ],
          "rotation":0,
          "type":"",
          "visible":true,
          "width":16,
          "x":224,
          "y":192
        },
        {
          "gid":2048,
          "height":16,
          "id":49,
          "name":"\u6d77\u8cca(\u4e0b\u3063\u7aef)",
          "properties":[
            {
              "name":"accept_action_direction",
              "type":"int",
              "value":15
            },
            {
              "name":"action_id",
              "type":"int",
              "value":4
            },
            {
              "name":"affected",
              "type":"bool",
              "value":false
            },
            {
              "name":"asset_id",
              "type":"int",
              "value":54
            },
            {
              "name":"birdview_puppet",
              "type":"bool",
              "value":false
            },
            {
              "name":"direction",
              "type":"int",
              "value":4
            },
            {
              "name":"entity_id",
              "type":"int",
              "value":47
            },
            {
              "name":"eye_contact",
              "type":"bool",
              "value":true
            },
            {
              "name":"flight_altitude_ratio",
              "type":"float",
              "value":1
            },
            {
              "name":"idling",
              "type":"bool",
              "value":false
            },
            {
              "name":"link_object_id",
              "type":"int",
              "value":0
            },
            {
              "name":"message_key",
              "type":"string",
              "value":"MSG_PBK_09"
            },
            {
              "name":"move_interval_id",
              "type":"int",
              "value":0
            },
            {
              "name":"move_speed_id",
              "type":"int",
              "value":0
            },
            {
              "name":"move_step",
              "type":"int",
              "value":0
            },
            {
              "name":"move_type",
              "type":"int",
              "value":1
            },
            {
              "name":"move_while_display_message",
              "type":"bool",
              "value":false
            },
            {
              "name":"object_id",
              "type":"int",
              "value":0
            },
            {
              "name":"object_type",
              "type":"int",
              "value":6
            },
            {
              "name":"pushed",
              "type":"bool",
              "value":true
            },
            {
              "name":"script_id",
              "type":"int",
              "value":0
            },
            {
              "name":"target_character_status_id",
              "type":"int",
              "value":0
            },
            {
              "name":"turn_around",
              "type":"bool",
              "value":true
            },
            {
              "name":"visible_minimap",
              "type":"bool",
              "value":false
            }
          ],
          "rotation":0,
          "type":"",
          "visible":true,
          "width":16,
          "x":192,
          "y":192
        }
      ],
      "opacity":1,
      "type":"objectgroup",
      "visible":true,
      "x":0,
      "y":0
    }
  ],
  "name":"ev_e_0009",
  "opacity":1,
  "type":"group",
  "visible":true,
  "x":0,
  "y":0,
  "width":55,
  "height":45
}
